mmcv/__init__.py
mmcv/_ext.cpython-310-x86_64-linux-gnu.so
mmcv/version.py
mmcv/arraymisc/__init__.py
mmcv/arraymisc/quantization.py
mmcv/cnn/__init__.py
mmcv/cnn/alexnet.py
mmcv/cnn/resnet.py
mmcv/cnn/vgg.py
mmcv/cnn/bricks/__init__.py
mmcv/cnn/bricks/activation.py
mmcv/cnn/bricks/context_block.py
mmcv/cnn/bricks/conv.py
mmcv/cnn/bricks/conv2d_adaptive_padding.py
mmcv/cnn/bricks/conv_module.py
mmcv/cnn/bricks/conv_ws.py
mmcv/cnn/bricks/depthwise_separable_conv_module.py
mmcv/cnn/bricks/drop.py
mmcv/cnn/bricks/generalized_attention.py
mmcv/cnn/bricks/hsigmoid.py
mmcv/cnn/bricks/hswish.py
mmcv/cnn/bricks/non_local.py
mmcv/cnn/bricks/norm.py
mmcv/cnn/bricks/padding.py
mmcv/cnn/bricks/plugin.py
mmcv/cnn/bricks/scale.py
mmcv/cnn/bricks/swish.py
mmcv/cnn/bricks/transformer.py
mmcv/cnn/bricks/upsample.py
mmcv/cnn/bricks/wrappers.py
mmcv/cnn/rfsearch/__init__.py
mmcv/cnn/rfsearch/operator.py
mmcv/cnn/rfsearch/search.py
mmcv/cnn/rfsearch/utils.py
mmcv/cnn/utils/__init__.py
mmcv/cnn/utils/flops_counter.py
mmcv/cnn/utils/fuse_conv_bn.py
mmcv/image/__init__.py
mmcv/image/colorspace.py
mmcv/image/geometric.py
mmcv/image/io.py
mmcv/image/misc.py
mmcv/image/photometric.py
mmcv/ops/__init__.py
mmcv/ops/active_rotated_filter.py
mmcv/ops/assign_score_withk.py
mmcv/ops/ball_query.py
mmcv/ops/bbox.py
mmcv/ops/bezier_align.py
mmcv/ops/bias_act.py
mmcv/ops/border_align.py
mmcv/ops/box_iou_quadri.py
mmcv/ops/box_iou_rotated.py
mmcv/ops/carafe.py
mmcv/ops/cc_attention.py
mmcv/ops/chamfer_distance.py
mmcv/ops/contour_expand.py
mmcv/ops/conv2d_gradfix.py
mmcv/ops/convex_iou.py
mmcv/ops/corner_pool.py
mmcv/ops/correlation.py
mmcv/ops/deform_conv.py
mmcv/ops/deform_roi_pool.py
mmcv/ops/deprecated_wrappers.py
mmcv/ops/diff_iou_rotated.py
mmcv/ops/filtered_lrelu.py
mmcv/ops/focal_loss.py
mmcv/ops/furthest_point_sample.py
mmcv/ops/fused_bias_leakyrelu.py
mmcv/ops/gather_points.py
mmcv/ops/group_points.py
mmcv/ops/info.py
mmcv/ops/iou3d.py
mmcv/ops/knn.py
mmcv/ops/masked_conv.py
visaionmmcv-2.1.1.dist-info/licenses/LICENSE
visaionmmcv-2.1.1.dist-info/licenses/LICENSES.md
visaionmmcv-2.1.1.dist-info/METADATA
visaionmmcv-2.1.1.dist-info/WHEEL
visaionmmcv-2.1.1.dist-info/top_level.txt
visaionmmcv-2.1.1.dist-info/RECORD
